topos/__init__.py
topos/downloader.py
topos/env.py
topos/inference.py
toposv-0.1.2.dist-info/METADATA
toposv-0.1.2.dist-info/WHEEL
toposv-0.1.2.dist-info/entry_points.txt
toposv-0.1.2.dist-info/top_level.txt
toposv-0.1.2.dist-info/RECORD
