Metadata-Version: 2.4
Name: toposv
Version: 0.1.2
Summary: TOPOS: Target Organ Prediction of Scout Views for Automated CT Scan Planning
Home-page: https://github.com/sziegelmayer/TOPOS
Author: Sebastian Ziegelmayer, Tristan Lemke
Author-email: sziegelmayer@tum.de, tristan.lemke@tum.de
License: Apache-2.0
Classifier: Programming Language :: Python :: 3
Classifier: License :: OSI Approved :: Apache Software License
Classifier: Operating System :: OS Independent
Requires-Python: >=3.7
Requires-Dist: torch>=2.0
Requires-Dist: numpy>=1.24
Requires-Dist: nibabel>=5.0
Requires-Dist: nnunetv2>=1.0.0
Requires-Dist: blosc2
Requires-Dist: huggingface_hub>=0.17.0
Dynamic: author
Dynamic: author-email
Dynamic: classifier
Dynamic: description
Dynamic: description-content-type
Dynamic: home-page
Dynamic: license
Dynamic: requires-dist
Dynamic: requires-python
Dynamic: summary
